[
  {
    "title": "Free Usage",
    "description": "You can use our tools for free.",
    "image": "/images/features/noun_branding_1885335.svg"
  },
  {
    "title": "High quality A.I models",
    "description": "Our models are constantly changing to give you the best experince.",
    "image": "/images/features/noun_The Process_1885341.svg"
  },
  {
    "title": "Premium feature",
    "description": "Subsribe to enjoy our newly valuble features.",
    "image": "/images/features/noun_3d modeling_1885342.svg"
  }
]
